colorsimple/__init__.py
colorsimple/colorsimple.py
colorsimple-0.1.3.dist-info/LICENSE
colorsimple-0.1.3.dist-info/METADATA
colorsimple-0.1.3.dist-info/WHEEL
colorsimple-0.1.3.dist-info/top_level.txt
colorsimple-0.1.3.dist-info/RECORD
